README.md
setup.py
bin/convert-regions
genomic_regions/__init__.py
genomic_regions/config.py
genomic_regions/files.py
genomic_regions/helpers.py
genomic_regions/permute.py
genomic_regions/regions.py
genomic_regions/version.py
genomic_regions.egg-info/PKG-INFO
genomic_regions.egg-info/SOURCES.txt
genomic_regions.egg-info/dependency_links.txt
genomic_regions.egg-info/requires.txt
genomic_regions.egg-info/top_level.txt
genomic_regions/test/__init__.py
genomic_regions/test/test_regions.py