Metadata-Version: 1.0
Name: genomic-regions
Version: 0.0.9
Summary: Consistently handle genomic regions
Home-page: UNKNOWN
Author: UNKNOWN
Author-email: UNKNOWN
License: UNKNOWN
Platform: UNKNOWN
